{
  "stats": {
    "suites": 10,
    "tests": 15,
    "passes": 15,
    "pending": 0,
    "failures": 0,
    "start": "2019-11-04T16:54:32.396Z",
    "end": "2019-11-04T16:54:32.823Z",
    "duration": 427
  },
  "tests": [
    {
      "title": "sends a fetch request to 'https://www.googleapis.com/books/v1/volumes?maxResults=5&q=eragon'",
      "fullTitle": "books.js #initiateSearch(err, queryObj) sends a fetch request to 'https://www.googleapis.com/books/v1/volumes?maxResults=5&q=eragon'",
      "duration": 21,
      "currentRetry": 0,
      "err": {}
    },
    {
      "title": "Generates object with correct book information",
      "fullTitle": "books.js #generateSearchResults(booksData) Generates object with correct book information",
      "duration": 1,
      "currentRetry": 0,
      "err": {}
    },
    {
      "title": "Generates array with correct book titles",
      "fullTitle": "books.js #collectBookTitles(books) Generates array with correct book titles",
      "duration": 0,
      "currentRetry": 0,
      "err": {}
    },
    {
      "title": "should log the correct values to console",
      "fullTitle": "books.js #displayBooks(books) should log the correct values to console",
      "duration": 3,
      "currentRetry": 0,
      "err": {}
    },
    {
      "title": "should log the correct value to console",
      "fullTitle": "books.js #displayOptions() should log the correct value to console",
      "duration": 1,
      "currentRetry": 0,
      "err": {}
    },
    {
      "title": "should display bookList and options when passed 'list'",
      "fullTitle": "books.js #handleOptionSelection(err, selectionObj) should display bookList and options when passed 'list'",
      "duration": 2,
      "currentRetry": 0,
      "err": {}
    },
    {
      "title": "should initiate a new search when passed 'search'",
      "fullTitle": "books.js #handleOptionSelection(err, selectionObj) should initiate a new search when passed 'search'",
      "duration": 1,
      "currentRetry": 0,
      "err": {}
    },
    {
      "title": "should call addBookToList(book) when passed an integer",
      "fullTitle": "books.js #handleOptionSelection(err, selectionObj) should call addBookToList(book) when passed an integer",
      "duration": 1,
      "currentRetry": 0,
      "err": {}
    },
    {
      "title": "should call initiateOptionsPrompt when passed invalid selections",
      "fullTitle": "books.js #handleOptionSelection(err, selectionObj) should call initiateOptionsPrompt when passed invalid selections",
      "duration": 0,
      "currentRetry": 0,
      "err": {}
    },
    {
      "title": "should exit the program when passed 'exit'",
      "fullTitle": "books.js #handleOptionSelection(err, selectionObj) should exit the program when passed 'exit'",
      "duration": 0,
      "currentRetry": 0,
      "err": {}
    },
    {
      "title": "should initiate a new search when passed 'search'",
      "fullTitle": "books.js #handleListOptionSelection(err, selectionObj) should initiate a new search when passed 'search'",
      "duration": 1,
      "currentRetry": 0,
      "err": {}
    },
    {
      "title": "should call initiateListOptionsPrompt when passed invalid selections",
      "fullTitle": "books.js #handleListOptionSelection(err, selectionObj) should call initiateListOptionsPrompt when passed invalid selections",
      "duration": 1,
      "currentRetry": 0,
      "err": {}
    },
    {
      "title": "should exit the program when passed 'exit'",
      "fullTitle": "books.js #handleListOptionSelection(err, selectionObj) should exit the program when passed 'exit'",
      "duration": 1,
      "currentRetry": 0,
      "err": {}
    },
    {
      "title": "should create a new CLI proper default settings",
      "fullTitle": "cli.js CLI constructor should create a new CLI proper default settings",
      "duration": 0,
      "currentRetry": 0,
      "err": {}
    },
    {
      "title": "should create a new CLI proper settings",
      "fullTitle": "cli.js CLI constructor should create a new CLI proper settings",
      "duration": 1,
      "currentRetry": 0,
      "err": {}
    }
  ],
  "pending": [],
  "failures": [],
  "passes": [
    {
      "title": "sends a fetch request to 'https://www.googleapis.com/books/v1/volumes?maxResults=5&q=eragon'",
      "fullTitle": "books.js #initiateSearch(err, queryObj) sends a fetch request to 'https://www.googleapis.com/books/v1/volumes?maxResults=5&q=eragon'",
      "duration": 21,
      "currentRetry": 0,
      "err": {}
    },
    {
      "title": "Generates object with correct book information",
      "fullTitle": "books.js #generateSearchResults(booksData) Generates object with correct book information",
      "duration": 1,
      "currentRetry": 0,
      "err": {}
    },
    {
      "title": "Generates array with correct book titles",
      "fullTitle": "books.js #collectBookTitles(books) Generates array with correct book titles",
      "duration": 0,
      "currentRetry": 0,
      "err": {}
    },
    {
      "title": "should log the correct values to console",
      "fullTitle": "books.js #displayBooks(books) should log the correct values to console",
      "duration": 3,
      "currentRetry": 0,
      "err": {}
    },
    {
      "title": "should log the correct value to console",
      "fullTitle": "books.js #displayOptions() should log the correct value to console",
      "duration": 1,
      "currentRetry": 0,
      "err": {}
    },
    {
      "title": "should display bookList and options when passed 'list'",
      "fullTitle": "books.js #handleOptionSelection(err, selectionObj) should display bookList and options when passed 'list'",
      "duration": 2,
      "currentRetry": 0,
      "err": {}
    },
    {
      "title": "should initiate a new search when passed 'search'",
      "fullTitle": "books.js #handleOptionSelection(err, selectionObj) should initiate a new search when passed 'search'",
      "duration": 1,
      "currentRetry": 0,
      "err": {}
    },
    {
      "title": "should call addBookToList(book) when passed an integer",
      "fullTitle": "books.js #handleOptionSelection(err, selectionObj) should call addBookToList(book) when passed an integer",
      "duration": 1,
      "currentRetry": 0,
      "err": {}
    },
    {
      "title": "should call initiateOptionsPrompt when passed invalid selections",
      "fullTitle": "books.js #handleOptionSelection(err, selectionObj) should call initiateOptionsPrompt when passed invalid selections",
      "duration": 0,
      "currentRetry": 0,
      "err": {}
    },
    {
      "title": "should exit the program when passed 'exit'",
      "fullTitle": "books.js #handleOptionSelection(err, selectionObj) should exit the program when passed 'exit'",
      "duration": 0,
      "currentRetry": 0,
      "err": {}
    },
    {
      "title": "should initiate a new search when passed 'search'",
      "fullTitle": "books.js #handleListOptionSelection(err, selectionObj) should initiate a new search when passed 'search'",
      "duration": 1,
      "currentRetry": 0,
      "err": {}
    },
    {
      "title": "should call initiateListOptionsPrompt when passed invalid selections",
      "fullTitle": "books.js #handleListOptionSelection(err, selectionObj) should call initiateListOptionsPrompt when passed invalid selections",
      "duration": 1,
      "currentRetry": 0,
      "err": {}
    },
    {
      "title": "should exit the program when passed 'exit'",
      "fullTitle": "books.js #handleListOptionSelection(err, selectionObj) should exit the program when passed 'exit'",
      "duration": 1,
      "currentRetry": 0,
      "err": {}
    },
    {
      "title": "should create a new CLI proper default settings",
      "fullTitle": "cli.js CLI constructor should create a new CLI proper default settings",
      "duration": 0,
      "currentRetry": 0,
      "err": {}
    },
    {
      "title": "should create a new CLI proper settings",
      "fullTitle": "cli.js CLI constructor should create a new CLI proper settings",
      "duration": 1,
      "currentRetry": 0,
      "err": {}
    }
  ]
}